README.md
setup.py
src/mpfs2/__init__.py
src/mpfs2/mpfs2.py
src/mpfs2.egg-info/PKG-INFO
src/mpfs2.egg-info/SOURCES.txt
src/mpfs2.egg-info/dependency_links.txt
src/mpfs2.egg-info/entry_points.txt
src/mpfs2.egg-info/requires.txt
src/mpfs2.egg-info/top_level.txt