Metadata-Version: 2.1
Name: mpfs2
Version: 0.0.3
Summary: Extract files from a Microchip Proprietary File System (MPFS2)
Home-page: https://github.com/rene-d/mpfs2
Author: Rene Devichi
Author-email: rene.github@gmail.com
License: UNKNOWN
Project-URL: Source, https://github.com/rene-d/mpfs2
Project-URL: Bug Reports, https://github.com/rene-d/mpfs2/issues
Keywords: mpfs mpfs2
Platform: UNKNOWN
Classifier: Operating System :: OS Independent
Classifier: Programming Language :: Python :: 3
Classifier: Programming Language :: Python :: 3.6
Classifier: Programming Language :: Python :: 3.7
Classifier: Programming Language :: Python :: 3.8
Requires-Python: >=3.6
